{
  "name": "spx-typewriter",
  "description": "Animates text like it is being written on a typewriter.",
  "shadow": false,
  "properties": [
    {
      "name": "autoStart",
      "attribute": "auto-start",
      "type": "boolean",
      "description": "Automatically starts writing.",
      "default": "true",
      "defaultValue": "true",
      "tags": []
    },
    {
      "name": "delay",
      "attribute": "delay",
      "type": "any",
      "description": "Writing delay in ms. Also accepts 'natural' value.",
      "default": "'natural'",
      "defaultValue": "'natural'",
      "tags": []
    },
    {
      "name": "deleteSpeed",
      "attribute": "delete-speed",
      "type": "any",
      "description": "Delete delay in ms. Also accepts 'natural' value.",
      "default": "'natural'",
      "defaultValue": "'natural'",
      "tags": []
    },
    {
      "name": "display",
      "attribute": "display",
      "type": "string",
      "description": "",
      "default": "s.display",
      "defaultValue": "s.display",
      "tags": []
    },
    {
      "name": "loop",
      "attribute": "loop",
      "type": "boolean",
      "description": "Loops the animation.",
      "tags": []
    },
    {
      "name": "text",
      "attribute": "text",
      "type": "string",
      "description": "Text that should be written.",
      "default": "\"I'm a typewriter\"",
      "defaultValue": "\"I'm a typewriter\"",
      "tags": []
    }
  ],
  "events": [
    {
      "name": "spxTypewriterDidLoad",
      "description": "Fires after component has loaded."
    }
  ],
  "methods": [
    {
      "name": "play",
      "description": "Start animation.",
      "signature": "play() => Promise<void>"
    },
    {
      "name": "stop",
      "description": "Stop animation.",
      "signature": "stop() => Promise<void>"
    }
  ],
  "slots": [
    {
      "name": "inner",
      "description": "Slot (between HTML tags)."
    }
  ]
}