{
  "name": "spx-slideshow",
  "description": "Continuously playing slideshow.",
  "properties": [
    {
      "id": "slideshow-duration",
      "name": "duration",
      "type": "string",
      "description": "Duration of slideshow to complete one cycle.",
      "defaultValue": "'60s'",
      "tags": [
        {
          "name": "CSS"
        }
      ]
    },
    {
      "id": "slideshow-gap",
      "name": "gap",
      "type": "string",
      "description": "Gap between inner elements.",
      "defaultValue": "'var(--spx-space-lg)'",
      "tags": [
        {
          "name": "CSS"
        }
      ]
    },
    {
      "id": "slideshow-imageSize",
      "name": "imageSize",
      "type": "string",
      "description": "WordPress media size when using the helper function..",
      "tags": []
    },
    {
      "id": "slideshow-images",
      "name": "images",
      "type": "string",
      "description": "Gets images from an ACF or Metabox field.",
      "tags": [
        {
          "text": "&lt;?php spx\\get::gallery($fieldName, $type) ?>",
          "name": "helper"
        }
      ]
    },
    {
      "id": "slideshow-imagesSrc",
      "name": "imagesSrc",
      "type": "string",
      "description": "Gets images from an ACF or Metabox field.",
      "tags": [
        {
          "text": "'acf', 'mb'",
          "name": "choice"
        }
      ]
    },
    {
      "id": "slideshow-maxWidth",
      "name": "maxWidth",
      "type": "string",
      "description": "Max width of inner elements.",
      "defaultValue": "'350px'",
      "tags": [
        {
          "name": "CSS"
        }
      ]
    }
  ],
  "events": [],
  "methods": [],
  "slots": []
}